aerosol_optprop/__init__.py
aerosol_optprop/_version.py
aerosol_optprop/lognormal.py
aerosol_optprop/monodisperse.py
aerosol_optprop/piecewise_lognormal.py
aerosol_optprop/test_lognormal.py
aerosol_optprop/util.py
aerosol_optprop/data/refractive_index
aerosol_optprop-0.3.dist-info/METADATA
aerosol_optprop-0.3.dist-info/RECORD
aerosol_optprop-0.3.dist-info/WHEEL
aerosol_optprop-0.3.dist-info/top_level.txt
